json_dict_transformer/__init__.py
json_dict_transformer/main.py
json_dict_transformer-1.1.1.dist-info/METADATA
json_dict_transformer-1.1.1.dist-info/WHEEL
json_dict_transformer-1.1.1.dist-info/licenses/LICENSE
json_dict_transformer-1.1.1.dist-info/RECORD
