Metadata-Version: 2.1
Name: json_dict_transformer
Version: 1.1.1
Summary: Transform JSON into another JSON using schema
Project-URL: Homepage, https://github.com/thevops/json-dict-transformer
Author: Krzysztof Łuczak
License-File: LICENSE
Classifier: License :: OSI Approved :: MIT License
Classifier: Operating System :: OS Independent
Classifier: Programming Language :: Python :: 3
Requires-Python: >=3
